flem/__init__.py
flem/cli.py
flem/flem.py
flem/flow_func.py
flem/initialise.py
flem/read_dem.py
flem/solve_flem.py
flem-0.1.1.dist-info/AUTHORS.rst
flem-0.1.1.dist-info/LICENSE
flem-0.1.1.dist-info/METADATA
flem-0.1.1.dist-info/WHEEL
flem-0.1.1.dist-info/entry_points.txt
flem-0.1.1.dist-info/top_level.txt
flem-0.1.1.dist-info/RECORD
