Metadata-Version: 2.1
Name: flem
Version: 0.1.1
Summary: A simple diffusive landscape evolution model
Home-page: https://github.com/johnjarmitage/flem
Author: John Armitage
Author-email: john.joseph.armitage@gmail.com
License: MIT license
Keywords: flem
Platform: UNKNOWN
Classifier: Development Status :: 2 - Pre-Alpha
Classifier: Intended Audience :: Developers
Classifier: License :: OSI Approved :: MIT License
Classifier: Natural Language :: English
Classifier: Programming Language :: Python :: 3.7
Requires-Dist: Click (>=6.0)
